[
    {
        "date": "24/02/2006",
        "title": "New Year Celebrations Around the World",
        "author": "John Smith",
        "paragraph1": "People in different countries are celebrating the New Year with various traditions.",
        "image": "image1.png",
        "paragraph2": "Fireworks, parties, and family gatherings are common ways to ring in the new year.",
        "bibliography": "Marine Biology Research Journal"
    },
    {
        "date": "05/01/2006",
        "title": "Scientists Discover New Planet",
        "author": "Michael Johnson",
        "paragrafo1": "Astronomers have identified a new planet in a distant galaxy.",
        "image": "image2.png",
        "paragrafo2": "The planet is said to be similar in size to Earth and may have the potential to support life.",
        "bibliography": "Hollywood Gossip Magazine"
    },
    {
        "date": "09/02/2006",
        "title": "Tech Giant Launches Revolutionary Smartphone",
        "author": "Michael Johnson",
        "paragrafo1": "A leading technology company has unveiled its latest smartphone model.",
        "image": "image4.png",
        "paragrafo2": "The new device boasts advanced features and a sleek design, setting a new standard in the industry.",
        "bibliography": "Global News Network"
    },
    {
        "date": "12/01/2006",
        "title": "World Health Organization Issues Global Health Alert",
        "author": "Sophia Martinez",
        "paragrafo1": "The WHO has raised concerns about a new infectious disease spreading rapidly in several countries.",
        "image": "image3.png",
        "paragrafo2": "Health authorities are urging individuals to take precautions and stay informed about the situation.",
        "bibliography": "Vogue Magazine"
    },
    {
        "date": "08/01/2006",
        "title": "Stock Market Experiences Major Surge",
        "author": "John Smith",
        "paragrafo1": "Investors are rejoicing as the stock market sees a significant increase in value today.",
        "image": "image5.png",
        "paragrafo2": "Analysts attribute the rise to positive economic indicators and investor confidence.",
        "bibliography": "Space Exploration Journal"
    },
    {
        "date": "21/02/2006",
        "title": "Celebrity Couple Announces Divorce",
        "author": "Sophia Martinez",
        "paragrafo1": "A high-profile celebrity couple has decided to end their marriage after several years together.",
        "image": "image6.png",
        "paragrafo2": "The news has shocked fans and followers of the couple, who were considered a power couple in the entertainment industry.",
        "bibliography": "Hollywood Gossip Magazine"
    },
    {
        "date": "09/02/2006",
        "title": "New Study Reveals Health Benefits of Dark Chocolate",
        "author": "James Anderson",
        "paragrafo1": "Researchers have found that consuming dark chocolate in moderation can have positive effects on heart health.",
        "image": "image7.png",
        "paragrafo2": "The study suggests that the antioxidants present in dark chocolate contribute to these benefits.",
        "bibliography": "Space Exploration Journal"
    },
    {
        "date": "04/02/2006",
        "title": "Historic Landmark Undergoes Renovation",
        "author": "Michael Johnson",
        "paragrafo1": "A famous historical landmark is set to undergo a major renovation to preserve its cultural significance.",
        "image": "image8.png",
        "paragrafo2": "The renovation project aims to restore the landmark to its original glory while ensuring its longevity for future generations.",
        "bibliography": "Hollywood Gossip Magazine"
    },
    {
        "date": "23/01/2006",
        "title": "New Species of Fish Discovered in the Amazon River",
        "author": "Jane Doe",
        "paragrafo1": "Marine biologists have identified a previously unknown species of fish in the Amazon River.",
        "image": "image9.png",
        "paragrafo2": "The discovery highlights the rich biodiversity of the Amazon and the need for conservation efforts.",
        "bibliography": "Heritage Conservation Magazine"
    },
    {
        "date": "25/01/2006",
        "title": "Fashion Designer Launches Sustainable Clothing Line",
        "author": "Olivia Clark",
        "paragrafo1": "A renowned fashion designer has introduced a new clothing line made from eco-friendly materials.",
        "image": "image10.png",
        "paragrafo2": "The designer aims to promote sustainable fashion and reduce the industry's impact on the environment.",
        "bibliography": "Marine Biology Research Journal"
    },
    {
        "date": "18/02/2006",
        "title": "New Study Finds Link Between Sleep and Mental Health",
        "author": "Sarah Thompson",
        "paragrafo1": "Researchers have discovered a strong correlation between sleep patterns and mental health outcomes.",
        "image": "",
        "paragrafo2": "The study emphasizes the importance of prioritizing sleep for overall well-being.",
        "bibliography": "Heritage Conservation Magazine"
    },
    {
        "date": "26/01/2006",
        "title": "Tech Company Announces Breakthrough in Artificial Intelligence",
        "author": "Olivia Clark",
        "paragrafo1": "A leading tech company has made significant advancements in the field of artificial intelligence.",
        "image": "",
        "paragrafo2": "The new AI technology is said to be more efficient and capable of performing complex tasks.",
        "bibliography": "Hollywood Gossip Magazine"
    },
    {
        "date": "26/02/2006",
        "title": "New Study Reveals Impact of Climate Change on Coral Reefs",
        "author": "Sarah Thompson",
        "paragrafo1": "Scientists have found that rising ocean temperatures are causing widespread coral bleaching.",
        "image": "",
        "paragrafo2": "The study warns that if current trends continue, many coral reefs could be at risk of disappearing within the next few decades.",
        "bibliography": "Vogue Magazine"
    },
    {
        "date": "06/02/2006",
        "title": "Famous Author Announces New Book Release",
        "author": "Olivia Clark",
        "paragrafo1": "A bestselling author has announced the release of their highly anticipated new novel.",
        "image": "",
        "paragrafo2": "The book is expected to be a major hit and is already topping pre-order lists.",
        "bibliography": "Journal of Nutrition Science"
    },
    {
        "date": "30/01/2006",
        "title": "New Study Finds Link Between Exercise and Longevity",
        "author": "Sarah Thompson",
        "paragrafo1": "Researchers have discovered that regular physical activity is associated with a longer lifespan.",
        "image": "",
        "paragrafo2": "The study highlights the importance of incorporating exercise into daily routines for overall health.",
        "bibliography": "Hollywood Gossip Magazine"
    },
    {
        "date": "13/01/2006",
        "title": "Tech Company Acquires Startup for Innovative Technology",
        "author": "Emily Roberts",
        "paragrafo1": "A major tech company has acquired a startup known for its groundbreaking technology.",
        "image": "",
        "paragrafo2": "The acquisition is expected to enhance the company's product offerings and drive future growth.",
        "bibliography": "Space Exploration Journal"
    },
    {
        "date": "30/01/2006",
        "title": "New Study Reveals Benefits of Meditation on Mental Health",
        "author": "Michael Johnson",
        "paragrafo1": "Researchers have found that practicing meditation can significantly reduce symptoms of anxiety and depression.",
        "image": "",
        "paragrafo2": "The study suggests that incorporating mindfulness practices into daily life can improve overall mental well-being.",
        "bibliography": "Global News Network"
    },
    {
        "date": "08/01/2006",
        "title": "Historic City Hosts International Film Festival",
        "author": "Michael Johnson",
        "paragrafo1": "A famous city is set to host an international film festival, attracting filmmakers and celebrities from around the world.",
        "image": "",
        "paragrafo2": "The festival promises to showcase a diverse range of films and celebrate the art of cinema.",
        "bibliography": "Tech Today Magazine"
    },
    {
        "date": "02/03/2006",
        "title": "New Species of Bird Discovered in Madagascar",
        "author": "John Smith",
        "paragrafo1": "Ornithologists have identified a previously unknown species of bird in Madagascar.",
        "image": "",
        "paragrafo2": "The discovery highlights the unique biodiversity of the island and the need for conservation efforts.",
        "bibliography": "Marine Biology Research Journal"
    },
    {
        "date": "25/02/2006",
        "title": "Fashion Brand Collaborates with Celebrity for Limited Edition Collection",
        "author": "Michael Johnson",
        "paragrafo1": "A popular fashion brand has teamed up with a famous celebrity to create a limited edition clothing collection.",
        "image": "",
        "paragrafo2": "The collaboration is expected to be a major hit among fans and fashion enthusiasts alike.",
        "bibliography": "Global News Network"
    },
    {
        "date": "21/01/2006",
        "title": "Discovery of New Planet Similar to Earth",
        "author": "Jane Doe",
        "paragrafo1": "Astronomers have discovered a new planet that resembles Earth in many ways.",
        "image": "",
        "paragrafo2": "The planet is located in the habitable zone of its star, leading scientists to believe it may harbor life.",
        "bibliography": "NASA, Journal of Astrophysics"
    },
    {
        "date": "25/02/2006",
        "title": "New Vaccine Shows Promise Against Malaria",
        "author": "John Smith",
        "paragrafo1": "A groundbreaking vaccine has shown promising results during clinical trials for malaria.",
        "image": "",
        "paragrafo2": "Experts believe this could significantly reduce malaria cases in endemic regions.",
        "bibliography": "World Health Organization, Clinical Education Journal"
    },
    {
        "date": "23/01/2006",
        "title": "",
        "author": "Daniel Brown",
        "paragrafo1": "The Midwest is experiencing unprecedented heat waves affecting agricultural outputs.",
        "image": "",
        "paragrafo2": "",
        "bibliography": "Marine Biology Research Journal"
    },
    {
        "date": "13/02/2006",
        "title": "Technology Conference Highlights Future Innovations",
        "author": "Oliver Adams",
        "paragrafo1": "Technological advancements were showcased at the annual tech conference this week.",
        "image": "",
        "paragrafo2": "Experts discussed the future of AI, software development, and sustainable tech solutions.",
        "bibliography": "Marine Biology Research Journal"
    },
    {
        "date": "29/10/2006",
        "title": "New Study Links Diet to Mental Health",
        "author": "Oliver Adams",
        "paragrafo1": "A recent study has found a significant correlation between diet and mental health.",
        "image": "",
        "paragrafo2": "The findings suggest that a balanced diet can improve mental health and overall well-being.",
        "bibliography": "Journal of Psychology"
    },
    {
        "date": "09/01/2006",
        "title": "Nobel Prize Winners Announced",
        "author": "David Wilson",
        "paragrafo1": "The Nobel Prize winners for 2023 have been announced, recognizing significant contributions in various fields.",
        "image": "",
        "paragrafo2": "The awards ceremony celebrated achievements in science, literature, and peace.",
        "bibliography": "Tech Today Magazine"
    },
    {
        "date": "06/01/2006",
        "title": "Global Unemployment Rates Decline",
        "author": "Mia Roberts",
        "paragrafo1": "",
        "image": "",
        "paragrafo2": "",
        "bibliography": "Tech Industry News"
    },
    {
        "date": "03/11/2006",
        "title": "Breakthrough in Renewable Energy Technology",
        "author": "Emily Roberts",
        "paragrafo1": "Innovators have developed a new renewable energy technology that could revolutionize the market.",
        "image": "",
        "paragrafo2": "This breakthrough could significantly reduce reliance on fossil fuels and combat climate change.",
        "bibliography": "Journal of Public Health"
    },
    {
        "date": "13/01/2006",
        "title": "Community Recognized for Environmental Conservation",
        "author": "Sarah Thompson",
        "paragrafo1": "A local community has been recognized for its efforts in environmental conservation.",
        "image": "",
        "paragrafo2": "Initiatives like recycling programs and green spaces have made a notable impact.",
        "bibliography": "Tech Industry News"
    },
    {
        "date": "18/01/2006",
        "title": "SpaceX Successfully Launches Mars Mission",
        "author": "Sarah Thompson",
        "paragrafo1": "SpaceX has successfully launched a mission to explore Mars with advanced technology.",
        "image": "",
        "paragrafo2": "Scientists are excited about the potential for new discoveries on the red planet.",
        "bibliography": "Marine Conservation Journal"
    },
    {
        "date": "11/01/2006",
        "title": "",
        "author": "Henry Scott",
        "paragrafo1": "A newly launched AI application allows for instant translation of multiple languages.",
        "image": "",
        "paragrafo2": "This app aims to break down communication barriers between cultures.",
        "bibliography": "Hollywood Gossip Magazine"
    },
    {
        "date": "16/01/2006",
        "title": "",
        "author": "Mia Roberts",
        "paragrafo1": "Researchers have made a significant breakthrough in cancer treatment methods.",
        "image": "",
        "paragrafo2": "",
        "bibliography": "Journal of Nutrition Science"
    },
    {
        "date": "02/06/2006",
        "title": "Aliens Land on Earth to Share Knowledge",
        "author": "David Wilson",
        "paragrafo1": "",
        "image": "AI",
        "paragrafo2": "",
        "bibliography": "Literary News Magazine"
    },
    {
        "date": "24/01/2006",
        "title": "World's First Flying Car Now Available",
        "author": "Daniel Brown",
        "paragrafo1": "A company has released the world's first flying car, promising to change the way we travel.",
        "image": "AI",
        "paragrafo2": "The flying car is expected to revolutionize transportation and reduce traffic congestion.",
        "bibliography": "Financial Times"
    },
    {
        "date": "20/02/2006",
        "title": "Hear About the New Health Beverage That Makes You Live Forever?",
        "author": "Charlotte Green",
        "paragrafo1": "A new health beverage claims to offer miraculous benefits, including extended lifespan.",
        "image": "AI",
        "paragrafo2": "Critics warn against falling for such outrageous claims.",
        "bibliography": "Vogue Magazine"
    },
    {
        "date": "04/02/2006",
        "title": "",
        "author": "Henry Scott",
        "paragrafo1": "",
        "image": "AI",
        "paragrafo2": "This discovery has sparked interest and debates within the scientific community.",
        "bibliography": "Financial Times"
    },
    {
        "date": "07/02/2006",
        "title": "Chocolate Found to Cure All Diseases",
        "author": "Sophia Martinez",
        "paragrafo1": "Recent studies suggest that chocolate contains compounds that may have health benefits.",
        "image": "AI",
        "paragrafo2": "Many are skeptical of this claim and urge caution.",
        "bibliography": "Marine Biology Research Journal"
    },
    {
        "date": "28/03/2006",
        "title": "Government to Ban All Animals",
        "author": "Olivia Clark",
        "paragrafo1": "In an unexpected move, the government has proposed to ban all domestic animals for environmental reasons.",
        "image": "AI",
        "paragrafo2": "Citizens are outraged, claiming this measure is unnecessary.",
        "bibliography": "International Health News Network"
    },
    {
        "date": "28/02/2006",
        "title": "",
        "author": "Benjamin Lee",
        "paragrafo1": "",
        "image": "AI",
        "paragrafo2": "Fans are left confused and intrigued by the strange turn of events.",
        "bibliography": "Marine Biology Research Journal"
    },
    {
        "date": "27/01/2006",
        "title": "Documentary Claims Leaders Are Reptilian Aliens",
        "author": "Daniel Brown",
        "paragrafo1": "A new documentary claims to reveal that high-profile leaders are actually reptilian aliens.",
        "image": "AI",
        "paragrafo2": "The documentary has sparked widespread debate and conspiracy theories.",
        "bibliography": "Journal of Nutrition Science"
    },
    {
        "date": "07/01/2006",
        "title": "Scientist Claims Time Travel is Now Possible",
        "author": "Jane Doe",
        "paragrafo1": "A scientist has announced a breakthrough in time travel technology, claiming it is now possible.",
        "image": "AI",
        "paragrafo2": "Skeptics are eager to see tangible proof before believing.",
        "bibliography": "Journal of Public Health"
    },
    {
        "date": "19/01/2006",
        "title": "Mysterious Disappearance of a Town",
        "author": "Mia Roberts",
        "paragrafo1": "Residents woke up to find their entire town missing, with no explanation or trace of what happened.",
        "image": "AI",
        "paragrafo2": "Authorities are investigating the mysterious disappearance, leaving residents baffled and seeking answers.",
        "bibliography": "Literary News Magazine"
    }
]